{
 "creation": "2026-05-11 00:00:00.000000",
 "doctype": "DocType",
 "document_type": "",
 "editable_grid": 1,
 "engine": "InnoDB",
 "field_order": [
  "item_group",
  "category_label"
 ],
 "fields": [
  {
   "fieldname": "item_group",
   "fieldtype": "Link",
   "in_list_view": 1,
   "label": "Item Group",
   "options": "Item Group",
   "reqd": 1
  },
  {
   "fieldname": "category_label",
   "fieldtype": "Select",
   "in_list_view": 1,
   "label": "Category Label",
   "options": "Watches\nAccessories\nJewellery\nServices",
   "reqd": 1
  }
 ],
 "istable": 1,
 "links": [],
 "modified": "2026-05-11 00:00:00.000000",
 "modified_by": "Administrator",
 "module": "Aetas Customization",
 "name": "AOT Category Mapping",
 "owner": "Administrator",
 "permissions": [],
 "sort_field": "modified",
 "sort_order": "DESC"
}
